dtrackauditor/__init__.py
dtrackauditor/auditor.py
dtrackauditor/dtrackauditor.py
dtrack_auditor-1.5.0.dist-info/LICENSE
dtrack_auditor-1.5.0.dist-info/METADATA
dtrack_auditor-1.5.0.dist-info/WHEEL
dtrack_auditor-1.5.0.dist-info/entry_points.txt
dtrack_auditor-1.5.0.dist-info/top_level.txt
dtrack_auditor-1.5.0.dist-info/RECORD
