Metadata-Version: 2.1
Name: dtrack-auditor
Version: 1.5.0
Summary: Improved client for OWASP DependencyTrack usage in CI CD.
Home-page: https://github.com/thinksabin/DTrackAuditor
Author: thinksabin
License: Apache 2.0
Classifier: License :: OSI Approved :: Apache Software License
Classifier: Programming Language :: Python
Classifier: Programming Language :: Python :: 3
Classifier: Programming Language :: Python :: 3.7
Classifier: Programming Language :: Python :: 3.8
Classifier: Programming Language :: Python :: 3.9
Classifier: Programming Language :: Python :: 3.10
Classifier: Programming Language :: Python :: 3.11
Requires-Python: >=3.7.0
License-File: LICENSE
Requires-Dist: requests
Requires-Dist: polling
Requires-Dist: certifi
